jitlog/__init__.py
jitlog/__main__.py
jitlog/constants.py
jitlog/marks.py
jitlog/merge_point.py
jitlog/objects.py
jitlog/parser.py
jitlog/prettyprinter.py
jitlog/query.py
jitlog/upload.py
jitlog/test/__init__.py
jitlog/test/test_encoding.py
jitlog/test/test_jitlog.py
jitlog/test/test_query.py
vmprof/__init__.py
vmprof/__main__.py
vmprof/cli.py
vmprof/profiler.py
vmprof/reader.py
vmprof/show.py
vmprof/stats.py
vmprof/upload.py
vmprof/test/__init__.py
vmprof/test/cpuburn.py
vmprof/test/sqlite.py
vmprof/test/test_c_source.py
vmprof/test/test_c_symboltable.py
vmprof/test/test_config.py
vmprof/test/test_reader.py
vmprof/test/test_run.py
vmprof/test/test_stats.py
vmshare/__init__.py
vmshare/binary.py
vmshare/service.py
vmprof-0.4.18.1.dist-info/LICENSE
vmprof-0.4.18.1.dist-info/METADATA
vmprof-0.4.18.1.dist-info/WHEEL
vmprof-0.4.18.1.dist-info/entry_points.txt
vmprof-0.4.18.1.dist-info/top_level.txt
vmprof-0.4.18.1.dist-info/RECORD
