Metadata-Version: 2.1
Name: vmprof
Version: 0.4.18.1
Summary: Python's vmprof client
Home-page: https://github.com/vmprof/vmprof-python
Author: vmprof team
Author-email: fijal@baroquesoftware.com
Classifier: License :: OSI Approved :: MIT License
Classifier: Programming Language :: Python
Classifier: Programming Language :: Python :: 2.7
Classifier: Programming Language :: Python :: 3
Classifier: Programming Language :: Python :: Implementation :: CPython
Classifier: Programming Language :: Python :: Implementation :: PyPy
Requires-Python: <3.12
License-File: LICENSE
Requires-Dist: requests
Requires-Dist: six
Requires-Dist: pytz
Requires-Dist: colorama
